[{"datasetid": "reseau-lio", "recordid": "59fbd07bd97dd912c666b2a71079fd90b13f5ad5", "fields": {"file": {"id": "9bd5ef79fa139ccbce0511108584394b", "height": 300, "width": 300, "filename": "calendar.txt", "thumbnail": false, "format": "txt"}}, "record_timestamp": "2023-06-13T11:04:30.617+02:00"},{"datasetid": "reseau-lio", "recordid": "0245d027af1bccb300af37291a1a02123b660afe", "fields": {"file": {"id": "611b3cacd6455b342f16fd285bfe9466", "height": 300, "width": 300, "filename": "trips_extensions.txt", "thumbnail": false, "format": "txt"}}, "record_timestamp": "2023-06-13T11:04:31.185+02:00"},{"datasetid": "reseau-lio", "recordid": "c2b2a30bc03f13bb17bbdcd46f70e8ec95d6f069", "fields": {"file": {"id": "d39dc8f4edb7fa0cb7ed377a4b0f11f6", "height": 300, "width": 300, "filename": "calendar_dates.txt", "thumbnail": false, "format": "txt"}}, "record_timestamp": "2023-06-13T11:04:30.621+02:00"},{"datasetid": "reseau-lio", "recordid": "14054a547de86da3927267c44bd50cda904cb0f0", "fields": {"file": {"id": "75b3d5b82fd9a38c2046347d8b8667fe", "height": 300, "width": 300, "filename": "stops_extension.txt", "thumbnail": false, "format": "txt"}}, "record_timestamp": "2023-06-13T11:04:30.617+02:00"},{"datasetid": "reseau-lio", "recordid": "b389cfce831bc264c5e77f54f79e371d6531d506", "fields": {"file": {"id": "7068c8d492df76c5125fac081b5e09e9", "height": 300, "width": 300, "filename": "stops.txt", "thumbnail": false, "format": "txt"}}, "record_timestamp": "2023-06-13T11:04:30.617+02:00"},{"datasetid": "reseau-lio", "recordid": "94ab5e2a66bb2d4a9e5093a613bd697f797feb16", "fields": {"file": {"id": "56665320292cbe85f66c935ffffa6657", "height": 300, "width": 300, "filename": "feed_info.txt", "thumbnail": false, "format": "txt"}}, "record_timestamp": "2023-06-13T11:04:30.609+02:00"},{"datasetid": "reseau-lio", "recordid": "42a420f85f17a69083d043d29981d59bbdb3ef22", "fields": {"file": {"id": "92c45d9df99624d7e05e9ade35ba0ce8", "height": 300, "width": 300, "filename": "routes.txt", "thumbnail": false, "format": "txt"}}, "record_timestamp": "2023-06-13T11:04:30.617+02:00"},{"datasetid": "reseau-lio", "recordid": "a37a9bbcb642777cefb36eea636257463791dff1", "fields": {"file": {"id": "3cc9124c230b72e07df09e27c59eba88", "height": 300, "width": 300, "filename": "stop_times.txt", "thumbnail": false, "format": "txt"}}, "record_timestamp": "2023-06-13T11:04:31.221+02:00"},{"datasetid": "reseau-lio", "recordid": "4a61e211dc8b6acd5f5abcd52b44d9402f41e3e0", "fields": {"file": {"id": "7831854a320cbf4ea5b6b327cd4581af", "height": 300, "width": 300, "filename": "trips.txt", "thumbnail": false, "format": "txt"}}, "record_timestamp": "2023-06-13T11:04:31.185+02:00"},{"datasetid": "reseau-lio", "recordid": "8b1a1126a2a7496cf06682e47008542333d37870", "fields": {"file": {"id": "fab955344340f299bfeaacaf424537c5", "height": 300, "width": 300, "filename": "shapes.txt", "thumbnail": false, "format": "txt"}}, "record_timestamp": "2023-06-13T11:04:31.181+02:00"},{"datasetid": "reseau-lio", "recordid": "59f3a1f894605f9287ebdd0cc157d1ec08bd99b9", "fields": {"file": {"id": "d8787abcf6fcb68ccff8a0dea8cca133", "height": 300, "width": 300, "filename": "agency.txt", "thumbnail": false, "format": "txt"}}, "record_timestamp": "2023-06-13T11:04:30.609+02:00"},{"datasetid": "reseau-lio", "recordid": "493bdb82d34d345ed8532fe859b8c6ad200980fd", "fields": {"file": {"id": "0db2e812dcf848c298161182cd508259", "height": 300, "width": 300, "filename": "route_directions.txt", "thumbnail": false, "format": "txt"}}, "record_timestamp": "2023-06-13T11:04:30.617+02:00"}]